<?xml version="1.0" encoding="UTF-8"?>
<!DOCTYPE mapper PUBLIC "-//mybatis.org//DTD Mapper 3.0//EN" "http://mybatis.org/dtd/mybatis-3-mapper.dtd">
<mapper namespace="com.Ape.dao.DO_FriendsMapper">
  <resultMap id="BaseResultMap" type="com.Ape.dataObject.DO_Friends">
    <!--
      WARNING - @mbg.generated
      This element is automatically generated by MyBatis Generator, do not modify.
      This element was generated on Tue Mar 31 15:38:01 CDT 2020.
    -->
    <id column="usersId" jdbcType="INTEGER" property="usersid" />
    <result column="friends1" jdbcType="VARCHAR" property="friends1" />
    <result column="friends2" jdbcType="VARCHAR" property="friends2" />
    <result column="friends3" jdbcType="VARCHAR" property="friends3" />
    <result column="friends4" jdbcType="VARCHAR" property="friends4" />
    <result column="friends5" jdbcType="VARCHAR" property="friends5" />
    <result column="friends6" jdbcType="VARCHAR" property="friends6" />
    <result column="friends7" jdbcType="VARCHAR" property="friends7" />
    <result column="friends8" jdbcType="VARCHAR" property="friends8" />
    <result column="friends9" jdbcType="VARCHAR" property="friends9" />
    <result column="friends10" jdbcType="VARCHAR" property="friends10" />
    <result column="friends11" jdbcType="VARCHAR" property="friends11" />
    <result column="friends12" jdbcType="VARCHAR" property="friends12" />
    <result column="friends13" jdbcType="VARCHAR" property="friends13" />
    <result column="friends14" jdbcType="VARCHAR" property="friends14" />
    <result column="friends15" jdbcType="VARCHAR" property="friends15" />
    <result column="friends16" jdbcType="VARCHAR" property="friends16" />
    <result column="friends17" jdbcType="VARCHAR" property="friends17" />
    <result column="friends18" jdbcType="VARCHAR" property="friends18" />
    <result column="friends19" jdbcType="VARCHAR" property="friends19" />
    <result column="friends20" jdbcType="VARCHAR" property="friends20" />
  </resultMap>
  <sql id="Base_Column_List">
    <!--
      WARNING - @mbg.generated
      This element is automatically generated by MyBatis Generator, do not modify.
      This element was generated on Tue Mar 31 15:38:01 CDT 2020.
    -->
    usersId, friends1, friends2, friends3, friends4, friends5, friends6, friends7, friends8, 
    friends9, friends10, friends11, friends12, friends13, friends14, friends15, friends16, 
    friends17, friends18, friends19, friends20
  </sql>
  <select id="selectByPrimaryKey" parameterType="java.lang.Integer" resultMap="BaseResultMap">
    <!--
      WARNING - @mbg.generated
      This element is automatically generated by MyBatis Generator, do not modify.
      This element was generated on Tue Mar 31 15:38:01 CDT 2020.
    -->
    select 
    <include refid="Base_Column_List" />
    from friends
    where usersId = #{usersid,jdbcType=INTEGER}
  </select>
  <delete id="deleteByPrimaryKey" parameterType="java.lang.Integer">
    <!--
      WARNING - @mbg.generated
      This element is automatically generated by MyBatis Generator, do not modify.
      This element was generated on Tue Mar 31 15:38:01 CDT 2020.
    -->
    delete from friends
    where usersId = #{usersid,jdbcType=INTEGER}
  </delete>
  <insert id="insert" parameterType="com.Ape.dataObject.DO_Friends">
    <!--
      WARNING - @mbg.generated
      This element is automatically generated by MyBatis Generator, do not modify.
      This element was generated on Tue Mar 31 15:38:01 CDT 2020.
    -->
    insert into friends (usersId, friends1, friends2, 
      friends3, friends4, friends5, 
      friends6, friends7, friends8, 
      friends9, friends10, friends11, 
      friends12, friends13, friends14, 
      friends15, friends16, friends17, 
      friends18, friends19, friends20
      )
    values (#{usersid,jdbcType=INTEGER}, #{friends1,jdbcType=VARCHAR}, #{friends2,jdbcType=VARCHAR}, 
      #{friends3,jdbcType=VARCHAR}, #{friends4,jdbcType=VARCHAR}, #{friends5,jdbcType=VARCHAR}, 
      #{friends6,jdbcType=VARCHAR}, #{friends7,jdbcType=VARCHAR}, #{friends8,jdbcType=VARCHAR}, 
      #{friends9,jdbcType=VARCHAR}, #{friends10,jdbcType=VARCHAR}, #{friends11,jdbcType=VARCHAR}, 
      #{friends12,jdbcType=VARCHAR}, #{friends13,jdbcType=VARCHAR}, #{friends14,jdbcType=VARCHAR}, 
      #{friends15,jdbcType=VARCHAR}, #{friends16,jdbcType=VARCHAR}, #{friends17,jdbcType=VARCHAR}, 
      #{friends18,jdbcType=VARCHAR}, #{friends19,jdbcType=VARCHAR}, #{friends20,jdbcType=VARCHAR}
      )
  </insert>
  <insert id="insertSelective" parameterType="com.Ape.dataObject.DO_Friends">
    <!--
      WARNING - @mbg.generated
      This element is automatically generated by MyBatis Generator, do not modify.
      This element was generated on Tue Mar 31 15:38:01 CDT 2020.
    -->
    insert into friends
    <trim prefix="(" suffix=")" suffixOverrides=",">
      <if test="usersid != null">
        usersId,
      </if>
      <if test="friends1 != null">
        friends1,
      </if>
      <if test="friends2 != null">
        friends2,
      </if>
      <if test="friends3 != null">
        friends3,
      </if>
      <if test="friends4 != null">
        friends4,
      </if>
      <if test="friends5 != null">
        friends5,
      </if>
      <if test="friends6 != null">
        friends6,
      </if>
      <if test="friends7 != null">
        friends7,
      </if>
      <if test="friends8 != null">
        friends8,
      </if>
      <if test="friends9 != null">
        friends9,
      </if>
      <if test="friends10 != null">
        friends10,
      </if>
      <if test="friends11 != null">
        friends11,
      </if>
      <if test="friends12 != null">
        friends12,
      </if>
      <if test="friends13 != null">
        friends13,
      </if>
      <if test="friends14 != null">
        friends14,
      </if>
      <if test="friends15 != null">
        friends15,
      </if>
      <if test="friends16 != null">
        friends16,
      </if>
      <if test="friends17 != null">
        friends17,
      </if>
      <if test="friends18 != null">
        friends18,
      </if>
      <if test="friends19 != null">
        friends19,
      </if>
      <if test="friends20 != null">
        friends20,
      </if>
    </trim>
    <trim prefix="values (" suffix=")" suffixOverrides=",">
      <if test="usersid != null">
        #{usersid,jdbcType=INTEGER},
      </if>
      <if test="friends1 != null">
        #{friends1,jdbcType=VARCHAR},
      </if>
      <if test="friends2 != null">
        #{friends2,jdbcType=VARCHAR},
      </if>
      <if test="friends3 != null">
        #{friends3,jdbcType=VARCHAR},
      </if>
      <if test="friends4 != null">
        #{friends4,jdbcType=VARCHAR},
      </if>
      <if test="friends5 != null">
        #{friends5,jdbcType=VARCHAR},
      </if>
      <if test="friends6 != null">
        #{friends6,jdbcType=VARCHAR},
      </if>
      <if test="friends7 != null">
        #{friends7,jdbcType=VARCHAR},
      </if>
      <if test="friends8 != null">
        #{friends8,jdbcType=VARCHAR},
      </if>
      <if test="friends9 != null">
        #{friends9,jdbcType=VARCHAR},
      </if>
      <if test="friends10 != null">
        #{friends10,jdbcType=VARCHAR},
      </if>
      <if test="friends11 != null">
        #{friends11,jdbcType=VARCHAR},
      </if>
      <if test="friends12 != null">
        #{friends12,jdbcType=VARCHAR},
      </if>
      <if test="friends13 != null">
        #{friends13,jdbcType=VARCHAR},
      </if>
      <if test="friends14 != null">
        #{friends14,jdbcType=VARCHAR},
      </if>
      <if test="friends15 != null">
        #{friends15,jdbcType=VARCHAR},
      </if>
      <if test="friends16 != null">
        #{friends16,jdbcType=VARCHAR},
      </if>
      <if test="friends17 != null">
        #{friends17,jdbcType=VARCHAR},
      </if>
      <if test="friends18 != null">
        #{friends18,jdbcType=VARCHAR},
      </if>
      <if test="friends19 != null">
        #{friends19,jdbcType=VARCHAR},
      </if>
      <if test="friends20 != null">
        #{friends20,jdbcType=VARCHAR},
      </if>
    </trim>
  </insert>
  <update id="updateByPrimaryKeySelective" parameterType="com.Ape.dataObject.DO_Friends">
    <!--
      WARNING - @mbg.generated
      This element is automatically generated by MyBatis Generator, do not modify.
      This element was generated on Tue Mar 31 15:38:01 CDT 2020.
    -->
    update friends
    <set>
      <if test="friends1 != null">
        friends1 = #{friends1,jdbcType=VARCHAR},
      </if>
      <if test="friends2 != null">
        friends2 = #{friends2,jdbcType=VARCHAR},
      </if>
      <if test="friends3 != null">
        friends3 = #{friends3,jdbcType=VARCHAR},
      </if>
      <if test="friends4 != null">
        friends4 = #{friends4,jdbcType=VARCHAR},
      </if>
      <if test="friends5 != null">
        friends5 = #{friends5,jdbcType=VARCHAR},
      </if>
      <if test="friends6 != null">
        friends6 = #{friends6,jdbcType=VARCHAR},
      </if>
      <if test="friends7 != null">
        friends7 = #{friends7,jdbcType=VARCHAR},
      </if>
      <if test="friends8 != null">
        friends8 = #{friends8,jdbcType=VARCHAR},
      </if>
      <if test="friends9 != null">
        friends9 = #{friends9,jdbcType=VARCHAR},
      </if>
      <if test="friends10 != null">
        friends10 = #{friends10,jdbcType=VARCHAR},
      </if>
      <if test="friends11 != null">
        friends11 = #{friends11,jdbcType=VARCHAR},
      </if>
      <if test="friends12 != null">
        friends12 = #{friends12,jdbcType=VARCHAR},
      </if>
      <if test="friends13 != null">
        friends13 = #{friends13,jdbcType=VARCHAR},
      </if>
      <if test="friends14 != null">
        friends14 = #{friends14,jdbcType=VARCHAR},
      </if>
      <if test="friends15 != null">
        friends15 = #{friends15,jdbcType=VARCHAR},
      </if>
      <if test="friends16 != null">
        friends16 = #{friends16,jdbcType=VARCHAR},
      </if>
      <if test="friends17 != null">
        friends17 = #{friends17,jdbcType=VARCHAR},
      </if>
      <if test="friends18 != null">
        friends18 = #{friends18,jdbcType=VARCHAR},
      </if>
      <if test="friends19 != null">
        friends19 = #{friends19,jdbcType=VARCHAR},
      </if>
      <if test="friends20 != null">
        friends20 = #{friends20,jdbcType=VARCHAR},
      </if>
    </set>
    where usersId = #{usersid,jdbcType=INTEGER}
  </update>
  <update id="updateByPrimaryKey" parameterType="com.Ape.dataObject.DO_Friends">
    <!--
      WARNING - @mbg.generated
      This element is automatically generated by MyBatis Generator, do not modify.
      This element was generated on Tue Mar 31 15:38:01 CDT 2020.
    -->
    update friends
    set friends1 = #{friends1,jdbcType=VARCHAR},
      friends2 = #{friends2,jdbcType=VARCHAR},
      friends3 = #{friends3,jdbcType=VARCHAR},
      friends4 = #{friends4,jdbcType=VARCHAR},
      friends5 = #{friends5,jdbcType=VARCHAR},
      friends6 = #{friends6,jdbcType=VARCHAR},
      friends7 = #{friends7,jdbcType=VARCHAR},
      friends8 = #{friends8,jdbcType=VARCHAR},
      friends9 = #{friends9,jdbcType=VARCHAR},
      friends10 = #{friends10,jdbcType=VARCHAR},
      friends11 = #{friends11,jdbcType=VARCHAR},
      friends12 = #{friends12,jdbcType=VARCHAR},
      friends13 = #{friends13,jdbcType=VARCHAR},
      friends14 = #{friends14,jdbcType=VARCHAR},
      friends15 = #{friends15,jdbcType=VARCHAR},
      friends16 = #{friends16,jdbcType=VARCHAR},
      friends17 = #{friends17,jdbcType=VARCHAR},
      friends18 = #{friends18,jdbcType=VARCHAR},
      friends19 = #{friends19,jdbcType=VARCHAR},
      friends20 = #{friends20,jdbcType=VARCHAR}
    where usersId = #{usersid,jdbcType=INTEGER}
  </update>
</mapper>